Workbook

Sheet 01_Instrucciones
A1: SEGUIMIENTO FINANCIERO — CONTRATOS PGP DUSAKAWI EPSI
A2: Archivo genérico de seguimiento mensual, trimestral y anual
A4: ESTRUCTURA DEL ARCHIVO
B5: HOJA | C5: CONTENIDO | D5: TIPO
B6: 01_Instrucciones | C6: Guía de uso del archivo. No requiere diligenciamiento. | D6: Lectura
B7: 02_Datos_Contrato | C7: Información base del contrato (IPS, valor, franja, % riesgo compartido, etc.). | D7: INPUT
B8: 03_Nota_Tecnica | C8: Actividades contratadas con frecuencia y tarifa. Cálculo automático del valor anual. | D8: INPUT
B9: 04_Seguimiento_Mensual | C9: Registro mensual del valor ejecutado. Cálculos automáticos de cumplimiento. | D9: INPUT + AUTO
B10: 05_Seguimiento_Trimestral | C10: Consolidado por trimestre con evaluación frente a franja de riesgo. | D10: AUTO
B11: 06_Cierre_Anual | C11: Consolidado anual con descuentos y reconocimientos aplicados al cierre. | D11: AUTO
B12: 07_Alertas_Semaforo | C12: Tablero visual de alertas mensuales y trimestrales. | D12: AUTO
A15: CÓDIGO DE COLORES
B16: Fondo amarillo claro + texto azul | C16: Celda de INPUT (usted debe diligenciar este valor)
B17: Fondo gris claro + texto negro | C17: Celda de CÁLCULO AUTOMÁTICO (no modificar)
B18: Texto verde | C18: Referencia a otra hoja del mismo archivo
B19: Resaltado verde (fondo) | C19: Valor dentro de franja de riesgo pactada (90 %–110 %)
B20: Resaltado amarillo (fondo) | C20: Alerta: cercano a límites de franja
B21: Resaltado rojo (fondo) | C21: Fuera de franja: requiere acción (descuento o reconocimiento)
A24: FLUJO DE DILIGENCIAMIENTO
B25: 1. Diligenciar la hoja '02_Datos_Contrato' con la información básica del contrato.
B26: 2. Diligenciar la hoja '03_Nota_Tecnica' con las actividades, frecuencias y tarifas pactadas. El valor anual se calcula automáticamente y debe ser verificado contra el valor contratado.
B27: 3. Mensualmente, registrar el valor ejecutado en la hoja '04_Seguimiento_Mensual'. Los cumplimientos, alertas y desviaciones se calculan automáticamente.
B28: 4. Al cierre de cada trimestre, revisar la hoja '05_Seguimiento_Trimestral' para validar la evaluación frente a franja de riesgo y los descuentos/reconocimientos aplicables.
B29: 5. Al cierre anual, la hoja '06_Cierre_Anual' consolida la información requerida para el acta final de ejecución y liquidación del contrato.
B30: 6. La hoja '07_Alertas_Semaforo' muestra el estado de cada mes y trimestre de forma visual.
A32: MODELO DE RIESGO COMPARTIDO (FÓRMULAS APLICADAS)
B33: • Franja de riesgo: permanencia de la ejecución entre el 90 % y el 110 % del valor proyectado.
B34: • Si la ejecución < 90 % del valor proyectado → se aplica DESCUENTO = (valor mínimo proyectado – ejecutado) × % riesgo compartido.
B35: • Si la ejecución > 110 % del valor proyectado → se aplica RECONOCIMIENTO = (ejecutado – valor máximo proyectado) × % riesgo compartido.
B36: • Si 90 % ≤ ejecución ≤ 110 % → sin ajuste financiero (dentro de franja, riesgo absorbido por el modelo PGP).
B37: • El porcentaje de riesgo compartido por defecto es 50 %, pero es editable en la hoja de datos del contrato.
B38: • Los ajustes se evalúan TRIMESTRALMENTE y se consolidan al cierre anual, conforme a la lógica propia del modelo PGP.

Sheet 02_Datos_Contrato
A1: DATOS GENERALES DEL CONTRATO PGP
A3: IDENTIFICACIÓN
B4: Número de contrato | C4: [Diligencie aquí]
B5: Fecha de suscripción | C5: DD/MM/AAAA
B6: Vigencia (fecha inicio) | C6: 46023
B7: Vigencia (fecha fin) | C7: 46387
B8: IPS / Unión Temporal contratada | C8: VITAL SALUD
B9: NIT | C9: 901226064-0
B10: Representante Legal | C10: ISELA MARIVETH MENGUAL BRTITO
B11: C.C. Representante Legal | C11: [Número]
B12: Servicio / objeto contractual | C12: SERVICIOS AMBULATORIO Y HOSPITALARIOS DE SALUD MENTAL
B13: Departamento | C13: LA GUAJIRA
B14: Municipio(s) | C14: ALBANIA, BARRANCAS, DIBULLA, DISTRACCION, FONSECA, HATONUECO, MAICAO, MANAURE, SAN JUAN DEL CESAR, RIOHACHA Y URIBIA
B15: Población objeto | C15: 170972
B16: Régimen (subsidiado / contributivo / mixto) | C16: SUB - CON
B17: Aplica enfoque diferencial indígena (SÍ/NO) | C17: SÍ
A19: PARÁMETROS FINANCIEROS DEL MODELO PGP
B20: Valor contratado INICIAL (anual) | C20: 3.4192694e+09 | D20: Valor pactado al inicio del contrato. No incluye ajustes posteriores.
B21: Valor mensual proyectado INICIAL | C21: =IF(C20>0,C20/12,0) -> 2.8493912e+08 | D21: Valor contratado inicial dividido en 12 meses (o periodo que aplique).
B22: ¿Hubo ajuste de nota técnica durante la vigencia? (SÍ/NO) | C22: NO | D22: Si hubo ajuste intermedio (como el caso de UROMIL), marque SÍ.
B23: Mes a partir del cual aplica el ajuste (1-12) | C23: 0 | D23: Número del mes desde el cual rige el nuevo valor. Dejar 0 si no aplica.
B24: Nuevo valor mensual proyectado (tras ajuste) | C24: 0 | D24: Valor mensual que rige a partir del mes indicado.
B25: Valor contratado FINAL (anual, con ajuste) | C25: =IF(C22="SÍ", C21*(C23-1)+C24*(12-C23+1), C20) -> 3.4192694e+09 | D25: Calculado: suma de meses al valor inicial + meses al valor ajustado.
B26: % Franja mínima de riesgo | C26: 0.9 | D26: Por defecto 90 %. Editable si el contrato pacta otro porcentaje.
B27: % Franja máxima de riesgo | C27: 1.1 | D27: Por defecto 110 %. Editable si el contrato pacta otro porcentaje.
B28: % Riesgo compartido (para descuentos y reconocimientos) | C28: 0.5 | D28: Porcentaje que se aplica al faltante o exceso. Por defecto 50 %.
B29: Límite inferior anual (franja 90 %) | C29: =C25*C26 -> 3.0773425e+09 | D29: Calculado automáticamente.
B30: Límite superior anual (franja 110 %) | C30: =C25*C27 -> 3.7611964e+09 | D30: Calculado automáticamente.
A32: RESPONSABLES DEL SEGUIMIENTO
B33: Coordinadora de Atención Complementaria y Alto Costo (Dusakawi) | C33: DIANA NAVARRO IZQUIERDO
B34: Asesor de la Dirección de Gestión del Riesgo (Dusakawi) | C34: ALEXANDER ARAUJO CASTILLO
B35: Auditor Concurrente (Dusakawi) | C35: [Nombre]
B36: Representante Legal IPS | C36: [Nombre]
B37: Gestor del contrato IPS | C37: [Nombre]

Sheet 03_Nota_Tecnica
A1: NOTA TÉCNICA — ACTIVIDADES CONTRATADAS
B2: Diligencie cada actividad con su frecuencia anual esperada y tarifa unitaria. El valor anual proyectado se calcula automáticamente.
B4: Ítem | C4: Código CUPS / actividad | D4: Descripción del servicio / procedimiento | E4: Frecuencia anual proyectada | F4: Tarifa unitaria ($) | G4: Valor anual proyectado ($) | H4: Valor mensual proyectado ($) | I4: % del contrato
B5: 1 | E5: 0 | F5: 0 | G5: =E5*F5 -> 0 | H5: =G5/12 -> 0 | I5: =IF($G$25>0,G5/$G$25,0) -> 0
B6: 2 | E6: 0 | F6: 0 | G6: =E6*F6 -> 0 | H6: =G6/12 -> 0 | I6: =IF($G$25>0,G6/$G$25,0) -> 0
B7: 3 | E7: 0 | F7: 0 | G7: =E7*F7 -> 0 | H7: =G7/12 -> 0 | I7: =IF($G$25>0,G7/$G$25,0) -> 0
B8: 4 | E8: 0 | F8: 0 | G8: =E8*F8 -> 0 | H8: =G8/12 -> 0 | I8: =IF($G$25>0,G8/$G$25,0) -> 0
B9: 5 | E9: 0 | F9: 0 | G9: =E9*F9 -> 0 | H9: =G9/12 -> 0 | I9: =IF($G$25>0,G9/$G$25,0) -> 0
B10: 6 | E10: 0 | F10: 0 | G10: =E10*F10 -> 0 | H10: =G10/12 -> 0 | I10: =IF($G$25>0,G10/$G$25,0) -> 0
B11: 7 | E11: 0 | F11: 0 | G11: =E11*F11 -> 0 | H11: =G11/12 -> 0 | I11: =IF($G$25>0,G11/$G$25,0) -> 0
B12: 8 | E12: 0 | F12: 0 | G12: =E12*F12 -> 0 | H12: =G12/12 -> 0 | I12: =IF($G$25>0,G12/$G$25,0) -> 0
B13: 9 | E13: 0 | F13: 0 | G13: =E13*F13 -> 0 | H13: =G13/12 -> 0 | I13: =IF($G$25>0,G13/$G$25,0) -> 0
B14: 10 | E14: 0 | F14: 0 | G14: =E14*F14 -> 0 | H14: =G14/12 -> 0 | I14: =IF($G$25>0,G14/$G$25,0) -> 0
B15: 11 | E15: 0 | F15: 0 | G15: =E15*F15 -> 0 | H15: =G15/12 -> 0 | I15: =IF($G$25>0,G15/$G$25,0) -> 0
B16: 12 | E16: 0 | F16: 0 | G16: =E16*F16 -> 0 | H16: =G16/12 -> 0 | I16: =IF($G$25>0,G16/$G$25,0) -> 0
... B24: 20 | E24: 0 | F24: 0 | G24: =E24*F24 -> 0 | H24: =G24/12 -> 0 | I24: =IF($G$25>0,G24/$G$25,0) -> 0
C25: TOTAL NOTA TÉCNICA | E25: =SUM(E5:E24) -> 0 | G25: =SUM(G5:G24) -> 0 | H25: =SUM(H5:H24) -> 0 | I25: =IF(G25>0,SUM(I5:I24),0) -> 0
B28: CONCILIACIÓN CON VALOR CONTRATADO
B29: Total Nota Técnica (suma de actividades) | H29: =G25 -> 0
B30: Valor contratado FINAL (hoja Datos Contrato) | H30: ='02_Datos_Contrato'!C25 -> 3.4192694e+09
B31: Diferencia (debe ser cero o cercana) | H31: =G25-'02_Datos_Contrato'!C25 -> -3.4192694e+09

Sheet 04_Seguimiento_Mensual
A1: SEGUIMIENTO MENSUAL DE EJECUCIÓN FINANCIERA
B2: Registre mensualmente el valor EJECUTADO. El valor proyectado, cumplimiento, desviación y estado se calculan automáticamente.
B4: # | C4: Mes | D4: Valor proyectado ($) | E4: Valor ejecutado ($) | F4: Desviación ($) | G4: % cumplimiento | H4: Estado franja | I4: Ejecutado acumulado ($) | J4: Observaciones / acciones
B5: 1 | C5: Enero | D5: =IF('02_Datos_Contrato'!C22="SÍ", IF(B5>='02_Datos_Contrato'!C23, '02_Datos_Contrato'!C24, '02_Datos_Contrato'!C21), '02_Datos_Contrato'!C21) -> 2.8493912e+08 | F5: =E5-D5 -> -2.8493912e+08 | G5: =IF(D5>0,E5/D5,0) -> 0 | H5: =IF(E5=0,"Sin registro",IF(G5<'02_Datos_Contrato'!$C$26,"Fuera - subejecución",IF(G5>'02_Datos_Contrato'!$C$27,"Fuera - sobreejecución","Dentro de franja"))) -> Sin registro | I5: =SUM($E$5:E5) -> 0
B6: 2 | C6: Febrero | D6: =IF('02_Datos_Contrato'!C22="SÍ", IF(B6>='02_Datos_Contrato'!C23, '02_Datos_Contrato'!C24, '02_Datos_Contrato'!C21), '02_Datos_Contrato'!C21) -> 2.8493912e+08 | F6: =E6-D6 -> -2.8493912e+08 | G6: =IF(D6>0,E6/D6,0) -> 0 | H6: =IF(E6=0,"Sin registro",IF(G6<'02_Datos_Contrato'!$C$26,"Fuera - subejecución",IF(G6>'02_Datos_Contrato'!$C$27,"Fuera - sobreejecución","Dentro de franja"))) -> Sin registro | I6: =SUM($E$5:E6) -> 0
B7: 3 | C7: Marzo | D7: =IF('02_Datos_Contrato'!C22="SÍ", IF(B7>='02_Datos_Contrato'!C23, '02_Datos_Contrato'!C24, '02_Datos_Contrato'!C21), '02_Datos_Contrato'!C21) -> 2.8493912e+08 | F7: =E7-D7 -> -2.8493912e+08 | G7: =IF(D7>0,E7/D7,0) -> 0 | H7: =IF(E7=0,"Sin registro",IF(G7<'02_Datos_Contrato'!$C$26,"Fuera - subejecución",IF(G7>'02_Datos_Contrato'!$C$27,"Fuera - sobreejecución","Dentro de franja"))) -> Sin registro | I7: =SUM($E$5:E7) -> 0
B8: 4 | C8: Abril | D8: =IF('02_Datos_Contrato'!C22="SÍ", IF(B8>='02_Datos_Contrato'!C23, '02_Datos_Contrato'!C24, '02_Datos_Contrato'!C21), '02_Datos_Contrato'!C21) -> 2.8493912e+08 | E8: 0 | F8: =E8-D8 -> -2.8493912e+08 | G8: =IF(D8>0,E8/D8,0) -> 0 | H8: =IF(E8=0,"Sin registro",IF(G8<'02_Datos_Contrato'!$C$26,"Fuera - subejecución",IF(G8>'02_Datos_Contrato'!$C$27,"Fuera - sobreejecución","Dentro de franja"))) -> Sin registro | I8: =SUM($E$5:E8) -> 0
B9: 5 | C9: Mayo | D9: =IF('02_Datos_Contrato'!C22="SÍ", IF(B9>='02_Datos_Contrato'!C23, '02_Datos_Contrato'!C24, '02_Datos_Contrato'!C21), '02_Datos_Contrato'!C21) -> 2.8493912e+08 | E9: 0 | F9: =E9-D9 -> -2.8493912e+08 | G9: =IF(D9>0,E9/D9,0) -> 0 | H9: =IF(E9=0,"Sin registro",IF(G9<'02_Datos_Contrato'!$C$26,"Fuera - subejecución",IF(G9>'02_Datos_Contrato'!$C$27,"Fuera - sobreejecución","Dentro de franja"))) -> Sin registro | I9: =SUM($E$5:E9) -> 0
B10: 6 | C10: Junio | D10: =IF('02_Datos_Contrato'!C22="SÍ", IF(B10>='02_Datos_Contrato'!C23, '02_Datos_Contrato'!C24, '02_Datos_Contrato'!C21), '02_Datos_Contrato'!C21) -> 2.8493912e+08 | E10: 0 | F10: =E10-D10 -> -2.8493912e+08 | G10: =IF(D10>0,E10/D10,0) -> 0 | H10: =IF(E10=0,"Sin registro",IF(G10<'02_Datos_Contrato'!$C$26,"Fuera - subejecución",IF(G10>'02_Datos_Contrato'!$C$27,"Fuera - sobreejecución","Dentro de franja"))) -> Sin registro | I10: =SUM($E$5:E10) -> 0
B11: 7 | C11: Julio | D11: =IF('02_Datos_Contrato'!C22="SÍ", IF(B11>='02_Datos_Contrato'!C23, '02_Datos_Contrato'!C24, '02_Datos_Contrato'!C21), '02_Datos_Contrato'!C21) -> 2.8493912e+08 | E11: 0 | F11: =E11-D11 -> -2.8493912e+08 | G11: =IF(D11>0,E11/D11,0) -> 0 | H11: =IF(E11=0,"Sin registro",IF(G11<'02_Datos_Contrato'!$C$26,"Fuera - subejecución",IF(G11>'02_Datos_Contrato'!$C$27,"Fuera - sobreejecución","Dentro de franja"))) -> Sin registro | I11: =SUM($E$5:E11) -> 0
B12: 8 | C12: Agosto | D12: =IF('02_Datos_Contrato'!C22="SÍ", IF(B12>='02_Datos_Contrato'!C23, '02_Datos_Contrato'!C24, '02_Datos_Contrato'!C21), '02_Datos_Contrato'!C21) -> 2.8493912e+08 | E12: 0 | F12: =E12-D12 -> -2.8493912e+08 | G12: =IF(D12>0,E12/D12,0) -> 0 | H12: =IF(E12=0,"Sin registro",IF(G12<'02_Datos_Contrato'!$C$26,"Fuera - subejecución",IF(G12>'02_Datos_Contrato'!$C$27,"Fuera - sobreejecución","Dentro de franja"))) -> Sin registro | I12: =SUM($E$5:E12) -> 0
B13: 9 | C13: Septiembre | D13: =IF('02_Datos_Contrato'!C22="SÍ", IF(B13>='02_Datos_Contrato'!C23, '02_Datos_Contrato'!C24, '02_Datos_Contrato'!C21), '02_Datos_Contrato'!C21) -> 2.8493912e+08 | E13: 0 | F13: =E13-D13 -> -2.8493912e+08 | G13: =IF(D13>0,E13/D13,0) -> 0 | H13: =IF(E13=0,"Sin registro",IF(G13<'02_Datos_Contrato'!$C$26,"Fuera - subejecución",IF(G13>'02_Datos_Contrato'!$C$27,"Fuera - sobreejecución","Dentro de franja"))) -> Sin registro | I13: =SUM($E$5:E13) -> 0
B14: 10 | C14: Octubre | D14: =IF('02_Datos_Contrato'!C22="SÍ", IF(B14>='02_Datos_Contrato'!C23, '02_Datos_Contrato'!C24, '02_Datos_Contrato'!C21), '02_Datos_Contrato'!C21) -> 2.8493912e+08 | E14: 0 | F14: =E14-D14 -> -2.8493912e+08 | G14: =IF(D14>0,E14/D14,0) -> 0 | H14: =IF(E14=0,"Sin registro",IF(G14<'02_Datos_Contrato'!$C$26,"Fuera - subejecución",IF(G14>'02_Datos_Contrato'!$C$27,"Fuera - sobreejecución","Dentro de franja"))) -> Sin registro | I14: =SUM($E$5:E14) -> 0
B15: 11 | C15: Noviembre | D15: =IF('02_Datos_Contrato'!C22="SÍ", IF(B15>='02_Datos_Contrato'!C23, '02_Datos_Contrato'!C24, '02_Datos_Contrato'!C21), '02_Datos_Contrato'!C21) -> 2.8493912e+08 | E15: 0 | F15: =E15-D15 -> -2.8493912e+08 | G15: =IF(D15>0,E15/D15,0) -> 0 | H15: =IF(E15=0,"Sin registro",IF(G15<'02_Datos_Contrato'!$C$26,"Fuera - subejecución",IF(G15>'02_Datos_Contrato'!$C$27,"Fuera - sobreejecución","Dentro de franja"))) -> Sin registro | I15: =SUM($E$5:E15) -> 0
B16: 12 | C16: Diciembre | D16: =IF('02_Datos_Contrato'!C22="SÍ", IF(B16>='02_Datos_Contrato'!C23, '02_Datos_Contrato'!C24, '02_Datos_Contrato'!C21), '02_Datos_Contrato'!C21) -> 2.8493912e+08 | E16: 0 | F16: =E16-D16 -> -2.8493912e+08 | G16: =IF(D16>0,E16/D16,0) -> 0 | H16: =IF(E16=0,"Sin registro",IF(G16<'02_Datos_Contrato'!$C$26,"Fuera - subejecución",IF(G16>'02_Datos_Contrato'!$C$27,"Fuera - sobreejecución","Dentro de franja"))) -> Sin registro | I16: =SUM($E$5:E16) -> 0
C17: TOTAL AÑO | D17: =SUM(D5:D16) -> 3.4192694e+09 | E17: =SUM(E5:E16) -> 0 | F17: =SUM(F5:F16) -> -3.4192694e+09 | G17: =IF(D17>0,E17/D17,0) -> 0 | I17: =E17 -> 0

Sheet 05_Seguimiento_Trimestral
A1: SEGUIMIENTO TRIMESTRAL Y EVALUACIÓN FRENTE A FRANJA DE RIESGO
B3: Trimestre | C3: Meses | D3: Proyectado ($) | E3: Ejecutado ($) | F3: % cumplimiento | G3: Límite inferior 90 % ($) | H3: Límite superior 110 % ($) | I3: Estado | J3: Faltante / Exceso ($) | K3: Descuento ($) | L3: Reconocimiento ($)
B4: I Trimestre | C4: Enero – Marzo | D4: ='04_Seguimiento_Mensual'!D5+'04_Seguimiento_Mensual'!D6+'04_Seguimiento_Mensual'!D7 -> 8.5481736e+08 | E4: ='04_Seguimiento_Mensual'!E5+'04_Seguimiento_Mensual'!E6+'04_Seguimiento_Mensual'!E7 -> 0 | F4: =IF(D4>0,E4/D4,0) -> 0 | G4: =D4*'02_Datos_Contrato'!$C$26 -> 7.6933562e+08 | H4: =D4*'02_Datos_Contrato'!$C$27 -> 9.4029909e+08 | I4: =IF(E4=0,"Sin ejecución",IF(F4<'02_Datos_Contrato'!$C$26,"Fuera - subejecución",IF(F4>'02_Datos_Contrato'!$C$27,"Fuera - sobreejecución","Dentro de franja"))) -> Sin ejecución | J4: =IF(I4="Fuera - subejecución",G4-E4,IF(I4="Fuera - sobreejecución",E4-H4,0)) -> 0 | K4: =IF(I4="Fuera - subejecución",J4*'02_Datos_Contrato'!$C$28,0) -> 0 | L4: =IF(I4="Fuera - sobreejecución",J4*'02_Datos_Contrato'!$C$28,0) -> 0
B5: II Trimestre | C5: Abril – Junio | D5: ='04_Seguimiento_Mensual'!D8+'04_Seguimiento_Mensual'!D9+'04_Seguimiento_Mensual'!D10 -> 8.5481736e+08 | E5: ='04_Seguimiento_Mensual'!E8+'04_Seguimiento_Mensual'!E9+'04_Seguimiento_Mensual'!E10 -> 0 | F5: =IF(D5>0,E5/D5,0) -> 0 | G5: =D5*'02_Datos_Contrato'!$C$26 -> 7.6933562e+08 | H5: =D5*'02_Datos_Contrato'!$C$27 -> 9.4029909e+08 | I5: =IF(E5=0,"Sin ejecución",IF(F5<'02_Datos_Contrato'!$C$26,"Fuera - subejecución",IF(F5>'02_Datos_Contrato'!$C$27,"Fuera - sobreejecución","Dentro de franja"))) -> Sin ejecución | J5: =IF(I5="Fuera - subejecución",G5-E5,IF(I5="Fuera - sobreejecución",E5-H5,0)) -> 0 | K5: =IF(I5="Fuera - subejecución",J5*'02_Datos_Contrato'!$C$28,0) -> 0 | L5: =IF(I5="Fuera - sobreejecución",J5*'02_Datos_Contrato'!$C$28,0) -> 0
B6: III Trimestre | C6: Julio – Septiembre | D6: ='04_Seguimiento_Mensual'!D11+'04_Seguimiento_Mensual'!D12+'04_Seguimiento_Mensual'!D13 -> 8.5481736e+08 | E6: ='04_Seguimiento_Mensual'!E11+'04_Seguimiento_Mensual'!E12+'04_Seguimiento_Mensual'!E13 -> 0 | F6: =IF(D6>0,E6/D6,0) -> 0 | G6: =D6*'02_Datos_Contrato'!$C$26 -> 7.6933562e+08 | H6: =D6*'02_Datos_Contrato'!$C$27 -> 9.4029909e+08 | I6: =IF(E6=0,"Sin ejecución",IF(F6<'02_Datos_Contrato'!$C$26,"Fuera - subejecución",IF(F6>'02_Datos_Contrato'!$C$27,"Fuera - sobreejecución","Dentro de franja"))) -> Sin ejecución | J6: =IF(I6="Fuera - subejecución",G6-E6,IF(I6="Fuera - sobreejecución",E6-H6,0)) -> 0 | K6: =IF(I6="Fuera - subejecución",J6*'02_Datos_Contrato'!$C$28,0) -> 0 | L6: =IF(I6="Fuera - sobreejecución",J6*'02_Datos_Contrato'!$C$28,0) -> 0
B7: IV Trimestre | C7: Octubre – Diciembre | D7: ='04_Seguimiento_Mensual'!D14+'04_Seguimiento_Mensual'!D15+'04_Seguimiento_Mensual'!D16 -> 8.5481736e+08 | E7: ='04_Seguimiento_Mensual'!E14+'04_Seguimiento_Mensual'!E15+'04_Seguimiento_Mensual'!E16 -> 0 | F7: =IF(D7>0,E7/D7,0) -> 0 | G7: =D7*'02_Datos_Contrato'!$C$26 -> 7.6933562e+08 | H7: =D7*'02_Datos_Contrato'!$C$27 -> 9.4029909e+08 | I7: =IF(E7=0,"Sin ejecución",IF(F7<'02_Datos_Contrato'!$C$26,"Fuera - subejecución",IF(F7>'02_Datos_Contrato'!$C$27,"Fuera - sobreejecución","Dentro de franja"))) -> Sin ejecución | J7: =IF(I7="Fuera - subejecución",G7-E7,IF(I7="Fuera - sobreejecución",E7-H7,0)) -> 0 | K7: =IF(I7="Fuera - subejecución",J7*'02_Datos_Contrato'!$C$28,0) -> 0 | L7: =IF(I7="Fuera - sobreejecución",J7*'02_Datos_Contrato'!$C$28,0) -> 0
B8: TOTAL ANUAL | D8: =SUM(D4:D7) -> 3.4192694e+09 | E8: =SUM(E4:E7) -> 0 | F8: =IF(D8>0,E8/D8,0) -> 0 | G8: =SUM(G4:G7) -> 3.0773425e+09 | H8: =SUM(H4:H7) -> 3.7611964e+09 | J8: =SUM(J4:J7) -> 0 | K8: =SUM(K4:K7) -> 0 | L8: =SUM(L4:L7) -> 0
B11: NOTAS METODOLÓGICAS
B12: • El valor proyectado trimestral se calcula a partir de la hoja 04_Seguimiento_Mensual, respetando el ajuste de nota técnica si fue informado.
B13: • Los descuentos se calculan sobre el FALTANTE frente al límite inferior (90 %) multiplicado por el % de riesgo compartido.
B14: • Los reconocimientos se calculan sobre el EXCESO frente al límite superior (110 %) multiplicado por el % de riesgo compartido.
B15: • Si el trimestre está dentro de franja (90 %–110 %), no se aplica descuento ni reconocimiento.
B16: • Los descuentos/reconocimientos trimestrales son acumulativos y deben documentarse en el acta parcial de cada trimestre.

Sheet 06_Cierre_Anual
A1: CIERRE ANUAL DE EJECUCIÓN FINANCIERA
A3: I. IDENTIFICACIÓN DEL CONTRATO
B4: Número de contrato | C4: ='02_Datos_Contrato'!C4 -> [Diligencie aquí]
B5: IPS / Unión Temporal | C5: ='02_Datos_Contrato'!C8 -> VITAL SALUD
B6: Servicio contratado | C6: ='02_Datos_Contrato'!C12 -> SERVICIOS AMBULATORIO Y HOSPITALARIOS DE SALUD MENTAL
B7: Territorio | C7: =CONCATENATE('02_Datos_Contrato'!C13," / ",'02_Datos_Contrato'!C14) -> LA GUAJIRA / ALBANIA, BARRANCAS, DIBULLA, DISTRACCION, FONSECA, HATONUECO, MAICAO, MANAURE, SAN JUAN DEL CESAR, RIOHACHA Y URIBIA
B8: Vigencia | C8: =CONCATENATE(TEXT('02_Datos_Contrato'!C6,"dd/mm/yyyy")," al ",TEXT('02_Datos_Contrato'!C7,"dd/mm/yyyy")) -> 01/01/2026 al 31/12/2026
A10: II. EJECUCIÓN FINANCIERA ANUAL (CONSOLIDADO)
B11: Valor contrato inicial | C11: ='02_Datos_Contrato'!C20 -> 3.4192694e+09
B12: Valor contratado FINAL (con ajuste, si aplica) | C12: ='02_Datos_Contrato'!C25 -> 3.4192694e+09
B13: Valor ejecutado ANUAL (suma mensual) | C13: ='04_Seguimiento_Mensual'!E17 -> 0
B14: % de cumplimiento anual | C14: =IF(C12>0,C13/C12,0) -> 0
B15: Valor sobre/sub ejecutado (ejecutado - contratado) | C15: =C13-C12 -> -3.4192694e+09
B16: Límite inferior anual (90 %) | C16: ='02_Datos_Contrato'!C29 -> 3.0773425e+09
B17: Límite superior anual (110 %) | C17: ='02_Datos_Contrato'!C30 -> 3.7611964e+09
B18: Estado anual frente a franja | C18: =IF(C13=0,"Sin ejecución",IF(C14<'02_Datos_Contrato'!$C$26,"Fuera - subejecución",IF(C14>'02_Datos_Contrato'!$C$27,"Fuera - sobreejecución","Dentro de franja"))) -> Sin ejecución
A20: III. AJUSTES FINANCIEROS POR RIESGO COMPARTIDO
B21: Descuentos trimestrales acumulados (por subejecución) | C21: ='05_Seguimiento_Trimestral'!K8 -> 0
B22: Reconocimientos trimestrales acumulados (por sobreejecución) | C22: ='05_Seguimiento_Trimestral'!L8 -> 0
B23: Saldo neto (descuentos - reconocimientos) | C23: =C21-C22 -> 0
B24: Naturaleza del saldo | C24: =IF(C23>0,"A favor de DUSAKAWI EPSI",IF(C23<0,"A favor de la IPS","Sin saldo")) -> Sin saldo
A26: IV. INSUMO PARA ACTA DE CIERRE
B27: Valor a reconocer en la liquidación | C27: =IF(C23<0,ABS(C23),0) -> 0
B28: Valor a descontar en la liquidación | C28: =IF(C23>0,C23,0) -> 0
B29: Observación para el acta | C29: =IF(C18="Dentro de franja","Comportamiento dentro de franja. Sin ajustes al cierre distintos a los ya aplicados trimestralmente.",IF(C18="Fuera - subejecución","Subejecución anual. Aplicar descuento al cierre conforme al modelo de riesgo compartido.",IF(C18="Fuera - sobreejecución","Sobreejecución anual. Aplicar reconocimiento al cierre conforme al modelo de riesgo compartido.","Sin ejecución registrada"))) -> Sin ejecución registrada

Sheet 07_Alertas_Semaforo
A1: TABLERO DE ALERTAS Y SEMÁFORO DE EJECUCIÓN
A3: ALERTAS MENSUALES
B4: Mes | C4: % cumplimiento | D4: Estado | E4: Desviación ($) | F4: Acción recomendada
B5: Enero | C5: ='04_Seguimiento_Mensual'!G5 -> 0 | D5: ='04_Seguimiento_Mensual'!H5 -> Sin registro | E5: ='04_Seguimiento_Mensual'!F5 -> -2.8493912e+08 | F5: =IF(D5="Sin registro","Pendiente de diligenciar valor ejecutado.",IF(D5="Dentro de franja","Mantener seguimiento de rutina.",IF(D5="Fuera - subejecución","REVISAR: analizar causas de baja ejecución y activar estrategias de captación y direccionamiento.","REVISAR: analizar causas de sobreejecución, verificar pertinencia clínica y evaluar ajuste de nota técnica."))) -> Pendiente de diligenciar valor ejecutado.
B6: Febrero | C6: ='04_Seguimiento_Mensual'!G6 -> 0 | D6: ='04_Seguimiento_Mensual'!H6 -> Sin registro | E6: ='04_Seguimiento_Mensual'!F6 -> -2.8493912e+08 | F6: =IF(D6="Sin registro","Pendiente de diligenciar valor ejecutado.",IF(D6="Dentro de franja","Mantener seguimiento de rutina.",IF(D6="Fuera - subejecución","REVISAR: analizar causas de baja ejecución y activar estrategias de captación y direccionamiento.","REVISAR: analizar causas de sobreejecución, verificar pertinencia clínica y evaluar ajuste de nota técnica."))) -> Pendiente de diligenciar valor ejecutado.
B7: Marzo | C7: ='04_Seguimiento_Mensual'!G7 -> 0 | D7: ='04_Seguimiento_Mensual'!H7 -> Sin registro | E7: ='04_Seguimiento_Mensual'!F7 -> -2.8493912e+08 | F7: =IF(D7="Sin registro","Pendiente de diligenciar valor ejecutado.",IF(D7="Dentro de franja","Mantener seguimiento de rutina.",IF(D7="Fuera - subejecución","REVISAR: analizar causas de baja ejecución y activar estrategias de captación y direccionamiento.","REVISAR: analizar causas de sobreejecución, verificar pertinencia clínica y evaluar ajuste de nota técnica."))) -> Pendiente de diligenciar valor ejecutado.
B8: Abril | C8: ='04_Seguimiento_Mensual'!G8 -> 0 | D8: ='04_Seguimiento_Mensual'!H8 -> Sin registro | E8: ='04_Seguimiento_Mensual'!F8 -> -2.8493912e+08 | F8: =IF(D8="Sin registro","Pendiente de diligenciar valor ejecutado.",IF(D8="Dentro de franja","Mantener seguimiento de rutina.",IF(D8="Fuera - subejecución","REVISAR: analizar causas de baja ejecución y activar estrategias de captación y direccionamiento.","REVISAR: analizar causas de sobreejecución, verificar pertinencia clínica y evaluar ajuste de nota técnica."))) -> Pendiente de diligenciar valor ejecutado.
B9: Mayo | C9: ='04_Seguimiento_Mensual'!G9 -> 0 | D9: ='04_Seguimiento_Mensual'!H9 -> Sin registro | E9: ='04_Seguimiento_Mensual'!F9 -> -2.8493912e+08 | F9: =IF(D9="Sin registro","Pendiente de diligenciar valor ejecutado.",IF(D9="Dentro de franja","Mantener seguimiento de rutina.",IF(D9="Fuera - subejecución","REVISAR: analizar causas de baja ejecución y activar estrategias de captación y direccionamiento.","REVISAR: analizar causas de sobreejecución, verificar pertinencia clínica y evaluar ajuste de nota técnica."))) -> Pendiente de diligenciar valor ejecutado.
B10: Junio | C10: ='04_Seguimiento_Mensual'!G10 -> 0 | D10: ='04_Seguimiento_Mensual'!H10 -> Sin registro | E10: ='04_Seguimiento_Mensual'!F10 -> -2.8493912e+08 | F10: =IF(D10="Sin registro","Pendiente de diligenciar valor ejecutado.",IF(D10="Dentro de franja","Mantener seguimiento de rutina.",IF(D10="Fuera - subejecución","REVISAR: analizar causas de baja ejecución y activar estrategias de captación y direccionamiento.","REVISAR: analizar causas de sobreejecución, verificar pertinencia clínica y evaluar ajuste de nota técnica."))) -> Pendiente de diligenciar valor ejecutado.
B11: Julio | C11: ='04_Seguimiento_Mensual'!G11 -> 0 | D11: ='04_Seguimiento_Mensual'!H11 -> Sin registro | E11: ='04_Seguimiento_Mensual'!F11 -> -2.8493912e+08 | F11: =IF(D11="Sin registro","Pendiente de diligenciar valor ejecutado.",IF(D11="Dentro de franja","Mantener seguimiento de rutina.",IF(D11="Fuera - subejecución","REVISAR: analizar causas de baja ejecución y activar estrategias de captación y direccionamiento.","REVISAR: analizar causas de sobreejecución, verificar pertinencia clínica y evaluar ajuste de nota técnica."))) -> Pendiente de diligenciar valor ejecutado.
B12: Agosto | C12: ='04_Seguimiento_Mensual'!G12 -> 0 | D12: ='04_Seguimiento_Mensual'!H12 -> Sin registro | E12: ='04_Seguimiento_Mensual'!F12 -> -2.8493912e+08 | F12: =IF(D12="Sin registro","Pendiente de diligenciar valor ejecutado.",IF(D12="Dentro de franja","Mantener seguimiento de rutina.",IF(D12="Fuera - subejecución","REVISAR: analizar causas de baja ejecución y activar estrategias de captación y direccionamiento.","REVISAR: analizar causas de sobreejecución, verificar pertinencia clínica y evaluar ajuste de nota técnica."))) -> Pendiente de diligenciar valor ejecutado.
B13: Septiembre | C13: ='04_Seguimiento_Mensual'!G13 -> 0 | D13: ='04_Seguimiento_Mensual'!H13 -> Sin registro | E13: ='04_Seguimiento_Mensual'!F13 -> -2.8493912e+08 | F13: =IF(D13="Sin registro","Pendiente de diligenciar valor ejecutado.",IF(D13="Dentro de franja","Mantener seguimiento de rutina.",IF(D13="Fuera - subejecución","REVISAR: analizar causas de baja ejecución y activar estrategias de captación y direccionamiento.","REVISAR: analizar causas de sobreejecución, verificar pertinencia clínica y evaluar ajuste de nota técnica."))) -> Pendiente de diligenciar valor ejecutado.
B14: Octubre | C14: ='04_Seguimiento_Mensual'!G14 -> 0 | D14: ='04_Seguimiento_Mensual'!H14 -> Sin registro | E14: ='04_Seguimiento_Mensual'!F14 -> -2.8493912e+08 | F14: =IF(D14="Sin registro","Pendiente de diligenciar valor ejecutado.",IF(D14="Dentro de franja","Mantener seguimiento de rutina.",IF(D14="Fuera - subejecución","REVISAR: analizar causas de baja ejecución y activar estrategias de captación y direccionamiento.","REVISAR: analizar causas de sobreejecución, verificar pertinencia clínica y evaluar ajuste de nota técnica."))) -> Pendiente de diligenciar valor ejecutado.
B15: Noviembre | C15: ='04_Seguimiento_Mensual'!G15 -> 0 | D15: ='04_Seguimiento_Mensual'!H15 -> Sin registro | E15: ='04_Seguimiento_Mensual'!F15 -> -2.8493912e+08 | F15: =IF(D15="Sin registro","Pendiente de diligenciar valor ejecutado.",IF(D15="Dentro de franja","Mantener seguimiento de rutina.",IF(D15="Fuera - subejecución","REVISAR: analizar causas de baja ejecución y activar estrategias de captación y direccionamiento.","REVISAR: analizar causas de sobreejecución, verificar pertinencia clínica y evaluar ajuste de nota técnica."))) -> Pendiente de diligenciar valor ejecutado.
B16: Diciembre | C16: ='04_Seguimiento_Mensual'!G16 -> 0 | D16: ='04_Seguimiento_Mensual'!H16 -> Sin registro | E16: ='04_Seguimiento_Mensual'!F16 -> -2.8493912e+08 | F16: =IF(D16="Sin registro","Pendiente de diligenciar valor ejecutado.",IF(D16="Dentro de franja","Mantener seguimiento de rutina.",IF(D16="Fuera - subejecución","REVISAR: analizar causas de baja ejecución y activar estrategias de captación y direccionamiento.","REVISAR: analizar causas de sobreejecución, verificar pertinencia clínica y evaluar ajuste de nota técnica."))) -> Pendiente de diligenciar valor ejecutado.
A19: CONTEO DE ALERTAS
B20: Meses dentro de franja | C20: =COUNTIF(D5:D16,"Dentro de franja") -> 0
B21: Meses en subejecución | C21: =COUNTIF(D5:D16,"Fuera - subejecución") -> 0
B22: Meses en sobreejecución | C22: =COUNTIF(D5:D16,"Fuera - sobreejecución") -> 0
B23: Meses sin registro | C23: =COUNTIF(D5:D16,"Sin registro") -> 12
A25: ESTADO TRIMESTRAL
B26: Trimestre | C26: % cumplimiento | D26: Estado | E26: Descuento ($) | F26: Reconocimiento ($)
B27: ='05_Seguimiento_Trimestral'!B4 -> I Trimestre | C27: ='05_Seguimiento_Trimestral'!F4 -> 0 | D27: ='05_Seguimiento_Trimestral'!I4 -> Sin ejecución | E27: ='05_Seguimiento_Trimestral'!K4 -> 0 | F27: ='05_Seguimiento_Trimestral'!L4 -> 0
B28: ='05_Seguimiento_Trimestral'!B5 -> II Trimestre | C28: ='05_Seguimiento_Trimestral'!F5 -> 0 | D28: ='05_Seguimiento_Trimestral'!I5 -> Sin ejecución | E28: ='05_Seguimiento_Trimestral'!K5 -> 0 | F28: ='05_Seguimiento_Trimestral'!L5 -> 0
B29: ='05_Seguimiento_Trimestral'!B6 -> III Trimestre | C29: ='05_Seguimiento_Trimestral'!F6 -> 0 | D29: ='05_Seguimiento_Trimestral'!I6 -> Sin ejecución | E29: ='05_Seguimiento_Trimestral'!K6 -> 0 | F29: ='05_Seguimiento_Trimestral'!L6 -> 0
B30: ='05_Seguimiento_Trimestral'!B7 -> IV Trimestre | C30: ='05_Seguimiento_Trimestral'!F7 -> 0 | D30: ='05_Seguimiento_Trimestral'!I7 -> Sin ejecución | E30: ='05_Seguimiento_Trimestral'!K7 -> 0 | F30: ='05_Seguimiento_Trimestral'!L7 -> 0
